<?xml version="1.0" encoding="utf-8" ?>
<dwsync>
<file name="connector.py" server="fishinginmichigan.net//home/webadmin/fishinginmichigan.net/html/" local="129234345940000000" remote="129234345940000000" />
<file name="wsgi.py" server="fishinginmichigan.net//home/webadmin/fishinginmichigan.net/html/" local="129234345970000000" remote="129234345970000000" />
<file name="htaccess.txt" server="fishinginmichigan.net//home/webadmin/fishinginmichigan.net/html/" local="129234345960000000" remote="129234345960000000" />
<file name="fckutil.py" server="fishinginmichigan.net//home/webadmin/fishinginmichigan.net/html/" local="129234345960000000" remote="129234345960000000" />
<file name="fckoutput.py" server="fishinginmichigan.net//home/webadmin/fishinginmichigan.net/html/" local="129234345950000000" remote="129234345950000000" />
<file name="upload.py" server="fishinginmichigan.net//home/webadmin/fishinginmichigan.net/html/" local="129234345960000000" remote="129234345960000000" />
<file name="zope.py" server="fishinginmichigan.net//home/webadmin/fishinginmichigan.net/html/" local="129234345970000000" remote="129234345970000000" />
<file name="fckcommands.py" server="fishinginmichigan.net//home/webadmin/fishinginmichigan.net/html/" local="129234345950000000" remote="129234345950000000" />
<file name="fckconnector.py" server="fishinginmichigan.net//home/webadmin/fishinginmichigan.net/html/" local="129234345950000000" remote="129234345950000000" />
<file name="config.py" server="fishinginmichigan.net//home/webadmin/fishinginmichigan.net/html/" local="129234345940000000" remote="129234345940000000" />
</dwsync>